{
  "type": "minecraft:entity",
  "pools": [
    {
      "rolls": 1,
      "entries": [
        {
          "type": "minecraft:item",
          "name": "monsters_level_up:wither_bone",
          "weight": 100,
          "functions": [
            {
              "function": "set_count",
              "count": {
                "min": 2,
                "max": 2
              }
            }
          ]
        }
      ]
    }
  ],
  "random_sequence": "monsters_level_up:entities/wither_skeleton_horsemen"
}